downpage/__init__.py
downpage/apps.py
downpage/generating.py
downpage/management/commands/__init__.py
downpage/management/commands/downpagegenerate.py
django_downpage-1.2.1.dist-info/LICENCE.txt
django_downpage-1.2.1.dist-info/METADATA
django_downpage-1.2.1.dist-info/WHEEL
django_downpage-1.2.1.dist-info/top_level.txt
django_downpage-1.2.1.dist-info/RECORD
