Metadata-Version: 2.1
Name: django-downpage
Version: 1.2.1
Summary: Generate static error pages (502 etc) for when your app is failing
Home-page: https://github.com/pscl4rke/django-downpage
Author: P. S. Clarke
Author-email: downpage@pscl4rke.net
License: cf:licence
Project-URL: Source Code, https://github.com/pscl4rke/django-downpage
Project-URL: Issues, https://github.com/pscl4rke/django-downpage/issues
Project-URL: Licence, https://github.com/pscl4rke/django-downpage/blob/master/LICENCE.txt
Classifier: Development Status :: 5 - Production/Stable
Classifier: Environment :: Web Environment
Classifier: Framework :: Django
Classifier: License :: OSI Approved :: BSD License
Classifier: Programming Language :: Python :: 3.8
Classifier: Programming Language :: Python :: 3.9
Classifier: Programming Language :: Python :: 3.10
Classifier: Programming Language :: Python :: 3.11
Classifier: Programming Language :: Python :: 3.12
Classifier: Programming Language :: Python :: 3.13
Classifier: Topic :: Internet :: WWW/HTTP
Requires-Python: >=3.8
License-File: LICENCE.txt
Requires-Dist: django (>=4)
Provides-Extra: testing
Requires-Dist: coverage ; extra == 'testing'
